odoo/addons/partner_mobile/README.rst
odoo/addons/partner_mobile/__init__.py
odoo/addons/partner_mobile/__manifest__.py
odoo/addons/partner_mobile/demo/res_partner.xml
odoo/addons/partner_mobile/i18n/it.po
odoo/addons/partner_mobile/i18n/partner_mobile.pot
odoo/addons/partner_mobile/models/__init__.py
odoo/addons/partner_mobile/models/res_partner.py
odoo/addons/partner_mobile/readme/CONTRIBUTORS.md
odoo/addons/partner_mobile/readme/DESCRIPTION.md
odoo/addons/partner_mobile/static/description/icon.png
odoo/addons/partner_mobile/static/description/index.html
odoo/addons/partner_mobile/views/res_partner.xml
odoo_addon_partner_mobile-19.0.1.0.0.4.dist-info/METADATA
odoo_addon_partner_mobile-19.0.1.0.0.4.dist-info/WHEEL
odoo_addon_partner_mobile-19.0.1.0.0.4.dist-info/top_level.txt
odoo_addon_partner_mobile-19.0.1.0.0.4.dist-info/RECORD
